{
	"sourceFile": "src/Html/index.astro",
	"activeCommit": 0,
	"commits": [
		{
			"activePatchIndex": 1,
			"patches": [
				{
					"date": 1688942538252,
					"content": "Index: \n===================================================================\n--- \n+++ \n"
				},
				{
					"date": 1688942556955,
					"content": "Index: \n===================================================================\n--- \n+++ \n@@ -5,9 +5,9 @@\n \n const { dir = \"ltr\", lang = \"en\" } = Astro.props;\n ---\n \n-<html {dir} lang={lang}>\n+<html {dir} {lang}>\n \t<slot />\n \n \n </html>\n"
				}
			],
			"date": 1688942538252,
			"name": "Commit-0",
			"content": "---\nimport type { HTMLAttributes } from \"astro/types\";\n\nexport type Props = HTMLAttributes<\"html\">;\n\nconst { dir = \"ltr\", lang = \"en\" } = Astro.props;\n---\n\n<html {dir} lang={lang}>\n\t<slot />\n\n</html>\n"
		}
	]
}
